robora/CONFIG.py
robora/__init__.py
robora/classes.py
robora/mock_query.py
robora/pandas_integration.py
robora/session_storage.py
robora/sonar_query.py
robora/sqlite_storage.py
robora/workflow.py
robora-0.0.18.dist-info/METADATA
robora-0.0.18.dist-info/WHEEL
robora-0.0.18.dist-info/top_level.txt
robora-0.0.18.dist-info/RECORD
